retaggr/__init__.py
retaggr/config.py
retaggr/core.py
retaggr/errors.py
retaggr/aiohttp_requests/__init__.py
retaggr/engines/__init__.py
retaggr/engines/base.py
retaggr/engines/danbooru.py
retaggr/engines/dummy.py
retaggr/engines/iqdb.py
retaggr/engines/paheal.py
retaggr/engines/saucenao/__init__.py
retaggr/engines/saucenao/engine.py
retaggr/engines/saucenao/handlers/__init__.py
retaggr/engines/saucenao/handlers/base.py
retaggr/engines/saucenao/handlers/danbooru.py
retaggr/engines/saucenao/handlers/e621.py
retaggr/engines/saucenao/handlers/gelbooru.py
retaggr/engines/saucenao/handlers/konachan.py
retaggr/engines/saucenao/handlers/yandere.py
retaggr-3.1.0.dist-info/LICENSE
retaggr-3.1.0.dist-info/METADATA
retaggr-3.1.0.dist-info/WHEEL
retaggr-3.1.0.dist-info/top_level.txt
retaggr-3.1.0.dist-info/RECORD
