Metadata-Version: 2.1
Name: retaggr
Version: 3.1.0
Summary: Reverse image searching utility for images.
Home-page: https://github.com/noirscape/retaggr
Author: Valentijn 'noirscape' V.
Author-email: neko@catgirlsin.space
License: LGPLv3
Project-URL: Source, https://github.com/noirscape/retaggr
Project-URL: Tracker, https://github.com/noirscape/retaggr/issues
Project-URL: Documentation, https://retaggr.rtfd.org
Keywords: reverse image search booru
Platform: UNKNOWN
Classifier: Development Status :: 5 - Production/Stable
Classifier: License :: OSI Approved :: GNU Lesser General Public License v3 (LGPLv3)
Classifier: Programming Language :: Python :: 3
Requires-Dist: lxml
Requires-Dist: fake-useragent
Requires-Dist: requests
Requires-Dist: aiohttp
